spark_tests/__init__.py
spark_tests/datetime.py
spark_tests/delta.py
spark_tests/sql.py
pyspark_tests-1.3.5.dist-info/LICENSE
pyspark_tests-1.3.5.dist-info/METADATA
pyspark_tests-1.3.5.dist-info/WHEEL
pyspark_tests-1.3.5.dist-info/top_level.txt
pyspark_tests-1.3.5.dist-info/RECORD
