Metadata-Version: 2.1
Name: pyspark-tests
Version: 1.3.5
Summary: A test framework for Python Spark application development
Home-page: https://github.com/susumuasaga/spark-tests
Author: Edson Susumu Asaga
Author-email: Edson Susumu Asaga <susumu.asaga@gmail.com.br>
Project-URL: Documentation, https://spark-tests.readthedocs.io/
Project-URL: Source, https://github.com/susumuasaga/spark-tests
Project-URL: Bug-tracker, https://github.com/susumuasaga/spark-tests/issues
Classifier: Programming Language :: Python :: 3
Classifier: License :: OSI Approved :: MIT License
Classifier: Operating System :: OS Independent
Requires-Python: >=3.6
License-File: LICENSE
